<?xml version="1.0" encoding="UTF-8"?>
<schemalist>
  <enum id='org.gnome.shell.extensions.gestureImprovements.animate-panel'>
    <value value='0' nick='NONE' />
    <value value='2' nick='MOVE_WINDOW' />
    <value value='3' nick='SWITCH_WORKSPACE_AND_MOVE_WINDOW' />
  </enum>
  <schema id="org.gnome.shell.extensions.gestureImprovements" path="/org/gnome/shell/extensions/gestureImprovements/">
    <!-- See also: https://developer.gnome.org/glib/stable/gvariant-format-strings.html -->
    <key name="touchpad-speed-scale" type="d">
      <default>1.0</default>
    </key>
    <key name="touchpad-pinch-speed" type="d">
      <default>1.0</default>
    </key>
    <key name="alttab-delay" type="i">
      <default>150</default>
    </key>
    <key name='default-session-workspace' type='b'>
      <default>false</default>
      <description>If true, use 3-fingers to switch workspace, 4 for windows</description>
    </key>
    <key name='default-overview' type='b'>
      <default>false</default>
      <description>If true, use 3-fingers for overview gesture, 4 for snapping/tiling</description>
    </key>
    <key name='allow-minimize-window' type='b'>
      <default>false</default>
      <description>If true, when swipe down on non-maximized window minimizes it</description>
    </key>
    <key name='follow-natural-scroll' type='b'>
      <default>true</default>
      <description>Whether to follow natural scroll for swipe</description>
    </key>
    <key name='enable-alttab-gesture' type='b'>
      <default>true</default>
      <description>Enable alttab gesture</description>
    </key>
    <key name='enable-window-manipulation-gesture' type='b'>
      <default>true</default>
      <description>Enable Window manipulation gesture</description>
    </key>
    <key name='enable-move-window-to-workspace' type='b'>
      <default>true</default>
      <description>Enable move window to workspace gesture</description>
    </key>
    <key name='enable-show-desktop' type='b'>
      <default>true</default>
      <description>Enable show desktop gesture</description>
    </key>
    <key name="animate-panel" enum="org.gnome.shell.extensions.gestureImprovements.animate-panel">
      <default>'MOVE_WINDOW'</default>
      <description>When to animate panel</description>
    </key>
  </schema>
</schemalist>